{
  "name": "geoffwilliams-aix_tidy",
  "version": "0.1.15",
  "author": "geoffwilliams",
  "summary": "Tidy up and lock down little AIX niggles",
  "license": "Apache-2.0",
  "source": "https://github.com/GeoffWilliams/aix_tidy",
  "project_page": "https://github.com/GeoffWilliams/aix_tidy",
  "issues_url": "https://github.com/GeoffWilliams/aix_tidy/issues",
  "dependencies": [
    {"name":"puppetlabs-stdlib","version_requirement":">= 1.0.0"},
    {"name":"geoffwilliams-chmod_r","version_requirement":"0.1.2"},
    {"name":"geoffwilliams-chown_r","version_requirement":"0.2.0"},
    {"name":"bwilcox-chsec", "version_requirement":"0.1.2"},
    {"name":"geoffwilliams-chrctcp", "version_requirement":"0.1.1"},
    {"name":"geoffwilliams-chsubserver", "version_requirement":"0.1.2"},
    {"name":"geoffwilliams-ssh", "version_requirement":"0.2.0"},
    {"name":"geoffwilliams-aix_no", "version_requirement":"0.1.1"}
  ],
  "data_provider": null
}
